[
  {
    "tick": 10,
    "population": 29,
    "avg_energy": 1.1333310388558169,
    "avg_age": 10.0,
    "avg_aggression": 0.35622645036864264,
    "avg_metabolism": 0.024184137357773694,
    "max_generation": 0,
    "births_this_period": 0,
    "deaths_this_period": 1,
    "species_counts": {
      "0": 6,
      "1": 6,
      "2": 6,
      "3": 6,
      "4": 5
    },
    "drive_distribution": {
      "hunger": 7,
      "fear": 0,
      "social": 22,
      "reproduce": 0
    }
  },
  {
    "tick": 20,
    "population": 27,
    "avg_energy": 1.171847431796637,
    "avg_age": 20.0,
    "avg_aggression": 0.34536773754919026,
    "avg_metabolism": 0.0236449661507146,
    "max_generation": 0,
    "births_this_period": 0,
    "deaths_this_period": 2,
    "species_counts": {
      "0": 6,
      "1": 6,
      "2": 5,
      "3": 5,
      "4": 5
    },
    "drive_distribution": {
      "hunger": 6,
      "fear": 0,
      "social": 21,
      "reproduce": 0
    }
  },
  {
    "tick": 30,
    "population": 35,
    "avg_energy": 1.0273720404883417,
    "avg_age": 23.6,
    "avg_aggression": 0.3534343113216866,
    "avg_metabolism": 0.024220417199447005,
    "max_generation": 1,
    "births_this_period": 8,
    "deaths_this_period": 0,
    "species_counts": {
      "0": 8,
      "1": 6,
      "2": 6,
      "3": 8,
      "4": 7
    },
    "drive_distribution": {
      "hunger": 7,
      "fear": 2,
      "social": 15,
      "reproduce": 11
    }
  },
  {
    "tick": 40,
    "population": 43,
    "avg_energy": 1.046045126048071,
    "avg_age": 27.302325581395348,
    "avg_aggression": 0.351517693504247,
    "avg_metabolism": 0.024219175002152548,
    "max_generation": 1,
    "births_this_period": 9,
    "deaths_this_period": 1,
    "species_counts": {
      "0": 11,
      "1": 8,
      "2": 7,
      "3": 8,
      "4": 9
    },
    "drive_distribution": {
      "hunger": 9,
      "fear": 2,
      "social": 20,
      "reproduce": 12
    }
  },
  {
    "tick": 50,
    "population": 50,
    "avg_energy": 1.0551670528751667,
    "avg_age": 31.76,
    "avg_aggression": 0.3524943327043403,
    "avg_metabolism": 0.02433880655974247,
    "max_generation": 2,
    "births_this_period": 8,
    "deaths_this_period": 1,
    "species_counts": {
      "0": 12,
      "1": 9,
      "2": 9,
      "3": 10,
      "4": 10
    },
    "drive_distribution": {
      "hunger": 3,
      "fear": 2,
      "social": 27,
      "reproduce": 18
    }
  },
  {
    "tick": 60,
    "population": 63,
    "avg_energy": 1.0953015543094569,
    "avg_age": 34.06349206349206,
    "avg_aggression": 0.3430724447062418,
    "avg_metabolism": 0.024572166176267656,
    "max_generation": 2,
    "births_this_period": 13,
    "deaths_this_period": 0,
    "species_counts": {
      "0": 16,
      "1": 9,
      "2": 12,
      "3": 14,
      "4": 12
    },
    "drive_distribution": {
      "hunger": 11,
      "fear": 3,
      "social": 28,
      "reproduce": 21
    }
  },
  {
    "tick": 70,
    "population": 82,
    "avg_energy": 1.2201461806652663,
    "avg_age": 35.01219512195122,
    "avg_aggression": 0.34508680638443384,
    "avg_metabolism": 0.024727051119118805,
    "max_generation": 2,
    "births_this_period": 19,
    "deaths_this_period": 0,
    "species_counts": {
      "0": 22,
      "1": 13,
      "2": 15,
      "3": 17,
      "4": 15
    },
    "drive_distribution": {
      "hunger": 26,
      "fear": 4,
      "social": 29,
      "reproduce": 23
    }
  },
  {
    "tick": 80,
    "population": 104,
    "avg_energy": 1.2524301397482458,
    "avg_age": 36.08653846153846,
    "avg_aggression": 0.3413692871626489,
    "avg_metabolism": 0.024497785159239782,
    "max_generation": 3,
    "births_this_period": 23,
    "deaths_this_period": 1,
    "species_counts": {
      "0": 28,
      "1": 16,
      "2": 20,
      "3": 23,
      "4": 17
    },
    "drive_distribution": {
      "hunger": 26,
      "fear": 9,
      "social": 37,
      "reproduce": 32
    }
  },
  {
    "tick": 90,
    "population": 136,
    "avg_energy": 1.2833013759149352,
    "avg_age": 34.3235294117647,
    "avg_aggression": 0.3349663699022439,
    "avg_metabolism": 0.024910154946092226,
    "max_generation": 3,
    "births_this_period": 35,
    "deaths_this_period": 3,
    "species_counts": {
      "0": 39,
      "1": 19,
      "2": 24,
      "3": 31,
      "4": 23
    },
    "drive_distribution": {
      "hunger": 53,
      "fear": 5,
      "social": 37,
      "reproduce": 41
    }
  },
  {
    "tick": 100,
    "population": 184,
    "avg_energy": 1.344179188546355,
    "avg_age": 33.92934782608695,
    "avg_aggression": 0.33861816356065544,
    "avg_metabolism": 0.024820799056612487,
    "max_generation": 4,
    "births_this_period": 48,
    "deaths_this_period": 0,
    "species_counts": {
      "0": 51,
      "1": 23,
      "2": 33,
      "3": 47,
      "4": 30
    },
    "drive_distribution": {
      "hunger": 77,
      "fear": 6,
      "social": 41,
      "reproduce": 60
    }
  },
  {
    "tick": 110,
    "population": 242,
    "avg_energy": 1.3469708800386413,
    "avg_age": 34.05785123966942,
    "avg_aggression": 0.33170001820038947,
    "avg_metabolism": 0.024268383431546234,
    "max_generation": 4,
    "births_this_period": 59,
    "deaths_this_period": 1,
    "species_counts": {
      "0": 66,
      "1": 31,
      "2": 46,
      "3": 64,
      "4": 35
    },
    "drive_distribution": {
      "hunger": 76,
      "fear": 45,
      "social": 57,
      "reproduce": 64
    }
  },
  {
    "tick": 120,
    "population": 313,
    "avg_energy": 1.259069876146451,
    "avg_age": 33.712460063897765,
    "avg_aggression": 0.32014390865967585,
    "avg_metabolism": 0.024062046134112582,
    "max_generation": 4,
    "births_this_period": 82,
    "deaths_this_period": 11,
    "species_counts": {
      "0": 81,
      "1": 45,
      "2": 61,
      "3": 88,
      "4": 38
    },
    "drive_distribution": {
      "hunger": 91,
      "fear": 82,
      "social": 65,
      "reproduce": 75
    }
  },
  {
    "tick": 130,
    "population": 405,
    "avg_energy": 1.2374392009451856,
    "avg_age": 34.40246913580247,
    "avg_aggression": 0.31759271283505697,
    "avg_metabolism": 0.023938491147483816,
    "max_generation": 5,
    "births_this_period": 96,
    "deaths_this_period": 4,
    "species_counts": {
      "0": 96,
      "1": 58,
      "2": 86,
      "3": 117,
      "4": 48
    },
    "drive_distribution": {
      "hunger": 144,
      "fear": 90,
      "social": 58,
      "reproduce": 113
    }
  },
  {
    "tick": 140,
    "population": 532,
    "avg_energy": 1.1657606156240303,
    "avg_age": 34.32706766917293,
    "avg_aggression": 0.31719213753536846,
    "avg_metabolism": 0.02382768190119283,
    "max_generation": 5,
    "births_this_period": 133,
    "deaths_this_period": 6,
    "species_counts": {
      "0": 120,
      "1": 72,
      "2": 114,
      "3": 163,
      "4": 63
    },
    "drive_distribution": {
      "hunger": 262,
      "fear": 131,
      "social": 41,
      "reproduce": 98
    }
  },
  {
    "tick": 150,
    "population": 645,
    "avg_energy": 1.0414964457856966,
    "avg_age": 36.2046511627907,
    "avg_aggression": 0.3157741141332709,
    "avg_metabolism": 0.023874827384132994,
    "max_generation": 6,
    "births_this_period": 122,
    "deaths_this_period": 9,
    "species_counts": {
      "0": 143,
      "1": 86,
      "2": 143,
      "3": 196,
      "4": 77
    },
    "drive_distribution": {
      "hunger": 287,
      "fear": 211,
      "social": 26,
      "reproduce": 121
    }
  },
  {
    "tick": 160,
    "population": 753,
    "avg_energy": 0.8764198562008322,
    "avg_age": 38.05444887118194,
    "avg_aggression": 0.3159609235375043,
    "avg_metabolism": 0.02345634634192673,
    "max_generation": 6,
    "births_this_period": 134,
    "deaths_this_period": 26,
    "species_counts": {
      "0": 156,
      "1": 97,
      "2": 174,
      "3": 235,
      "4": 91
    },
    "drive_distribution": {
      "hunger": 428,
      "fear": 198,
      "social": 10,
      "reproduce": 117
    }
  },
  {
    "tick": 170,
    "population": 831,
    "avg_energy": 0.7609920072003983,
    "avg_age": 40.76654632972323,
    "avg_aggression": 0.3181508816253268,
    "avg_metabolism": 0.02307279821853754,
    "max_generation": 6,
    "births_this_period": 112,
    "deaths_this_period": 34,
    "species_counts": {
      "0": 152,
      "1": 109,
      "2": 195,
      "3": 266,
      "4": 109
    },
    "drive_distribution": {
      "hunger": 521,
      "fear": 188,
      "social": 6,
      "reproduce": 116
    }
  },
  {
    "tick": 180,
    "population": 879,
    "avg_energy": 0.6750473007846745,
    "avg_age": 43.864618885096704,
    "avg_aggression": 0.3188835906534517,
    "avg_metabolism": 0.022675016265320133,
    "max_generation": 7,
    "births_this_period": 101,
    "deaths_this_period": 53,
    "species_counts": {
      "0": 143,
      "1": 117,
      "2": 216,
      "3": 289,
      "4": 114
    },
    "drive_distribution": {
      "hunger": 616,
      "fear": 137,
      "social": 4,
      "reproduce": 122
    }
  },
  {
    "tick": 190,
    "population": 890,
    "avg_energy": 0.6386654119745979,
    "avg_age": 47.2123595505618,
    "avg_aggression": 0.3203089819218618,
    "avg_metabolism": 0.022062040850966354,
    "max_generation": 7,
    "births_this_period": 86,
    "deaths_this_period": 75,
    "species_counts": {
      "0": 120,
      "1": 118,
      "2": 234,
      "3": 302,
      "4": 116
    },
    "drive_distribution": {
      "hunger": 683,
      "fear": 99,
      "social": 1,
      "reproduce": 107
    }
  },
  {
    "tick": 200,
    "population": 874,
    "avg_energy": 0.6144291839090171,
    "avg_age": 51.066361556064074,
    "avg_aggression": 0.32285861335693894,
    "avg_metabolism": 0.021595496870490918,
    "max_generation": 8,
    "births_this_period": 71,
    "deaths_this_period": 87,
    "species_counts": {
      "0": 94,
      "1": 121,
      "2": 238,
      "3": 304,
      "4": 117
    },
    "drive_distribution": {
      "hunger": 684,
      "fear": 85,
      "social": 1,
      "reproduce": 104
    }
  },
  {
    "tick": 210,
    "population": 842,
    "avg_energy": 0.6043959097797121,
    "avg_age": 54.76128266033254,
    "avg_aggression": 0.319921395934876,
    "avg_metabolism": 0.021061433459247436,
    "max_generation": 8,
    "births_this_period": 66,
    "deaths_this_period": 98,
    "species_counts": {
      "0": 90,
      "1": 118,
      "2": 231,
      "3": 293,
      "4": 110
    },
    "drive_distribution": {
      "hunger": 679,
      "fear": 54,
      "social": 2,
      "reproduce": 107
    }
  },
  {
    "tick": 220,
    "population": 829,
    "avg_energy": 0.582187595570791,
    "avg_age": 58.0518697225573,
    "avg_aggression": 0.31669088142059343,
    "avg_metabolism": 0.020678929299989247,
    "max_generation": 8,
    "births_this_period": 70,
    "deaths_this_period": 83,
    "species_counts": {
      "0": 76,
      "1": 115,
      "2": 221,
      "3": 305,
      "4": 112
    },
    "drive_distribution": {
      "hunger": 697,
      "fear": 40,
      "social": 2,
      "reproduce": 90
    }
  },
  {
    "tick": 230,
    "population": 792,
    "avg_energy": 0.5892738536685046,
    "avg_age": 62.16161616161616,
    "avg_aggression": 0.3142590391967812,
    "avg_metabolism": 0.020289982820552912,
    "max_generation": 9,
    "births_this_period": 51,
    "deaths_this_period": 88,
    "species_counts": {
      "0": 65,
      "1": 109,
      "2": 218,
      "3": 298,
      "4": 102
    },
    "drive_distribution": {
      "hunger": 650,
      "fear": 48,
      "social": 0,
      "reproduce": 94
    }
  },
  {
    "tick": 240,
    "population": 801,
    "avg_energy": 0.5997899752490953,
    "avg_age": 64.16978776529338,
    "avg_aggression": 0.3152317794822924,
    "avg_metabolism": 0.020102909100926266,
    "max_generation": 9,
    "births_this_period": 76,
    "deaths_this_period": 67,
    "species_counts": {
      "0": 62,
      "1": 110,
      "2": 210,
      "3": 311,
      "4": 108
    },
    "drive_distribution": {
      "hunger": 661,
      "fear": 44,
      "social": 0,
      "reproduce": 96
    }
  },
  {
    "tick": 250,
    "population": 799,
    "avg_energy": 0.6078669878395813,
    "avg_age": 66.50938673341678,
    "avg_aggression": 0.3118852067551702,
    "avg_metabolism": 0.019876490075590083,
    "max_generation": 10,
    "births_this_period": 66,
    "deaths_this_period": 68,
    "species_counts": {
      "0": 55,
      "1": 115,
      "2": 210,
      "3": 312,
      "4": 107
    },
    "drive_distribution": {
      "hunger": 675,
      "fear": 24,
      "social": 0,
      "reproduce": 100
    }
  },
  {
    "tick": 260,
    "population": 815,
    "avg_energy": 0.5992615658575611,
    "avg_age": 68.28588957055214,
    "avg_aggression": 0.311125860312534,
    "avg_metabolism": 0.019742372276069182,
    "max_generation": 10,
    "births_this_period": 76,
    "deaths_this_period": 60,
    "species_counts": {
      "0": 53,
      "1": 116,
      "2": 213,
      "3": 327,
      "4": 106
    },
    "drive_distribution": {
      "hunger": 695,
      "fear": 26,
      "social": 1,
      "reproduce": 93
    }
  },
  {
    "tick": 270,
    "population": 789,
    "avg_energy": 0.6070896639051571,
    "avg_age": 71.14955640050697,
    "avg_aggression": 0.3099202154769055,
    "avg_metabolism": 0.019483440722363906,
    "max_generation": 10,
    "births_this_period": 56,
    "deaths_this_period": 82,
    "species_counts": {
      "0": 45,
      "1": 122,
      "2": 202,
      "3": 320,
      "4": 100
    },
    "drive_distribution": {
      "hunger": 670,
      "fear": 17,
      "social": 0,
      "reproduce": 102
    }
  },
  {
    "tick": 280,
    "population": 811,
    "avg_energy": 0.5873964023588883,
    "avg_age": 72.3403205918619,
    "avg_aggression": 0.3074302693195687,
    "avg_metabolism": 0.01928358013927867,
    "max_generation": 10,
    "births_this_period": 78,
    "deaths_this_period": 56,
    "species_counts": {
      "0": 41,
      "1": 125,
      "2": 205,
      "3": 337,
      "4": 103
    },
    "drive_distribution": {
      "hunger": 691,
      "fear": 26,
      "social": 0,
      "reproduce": 94
    }
  },
  {
    "tick": 290,
    "population": 794,
    "avg_energy": 0.6034272512611503,
    "avg_age": 75.0352644836272,
    "avg_aggression": 0.3046200464938055,
    "avg_metabolism": 0.019072414545100377,
    "max_generation": 11,
    "births_this_period": 53,
    "deaths_this_period": 70,
    "species_counts": {
      "0": 39,
      "1": 119,
      "2": 200,
      "3": 335,
      "4": 101
    },
    "drive_distribution": {
      "hunger": 674,
      "fear": 22,
      "social": 1,
      "reproduce": 97
    }
  },
  {
    "tick": 300,
    "population": 808,
    "avg_energy": 0.6011221760397274,
    "avg_age": 75.66089108910892,
    "avg_aggression": 0.3039214374558633,
    "avg_metabolism": 0.018870699473607894,
    "max_generation": 11,
    "births_this_period": 73,
    "deaths_this_period": 59,
    "species_counts": {
      "0": 40,
      "1": 123,
      "2": 198,
      "3": 337,
      "4": 110
    },
    "drive_distribution": {
      "hunger": 696,
      "fear": 19,
      "social": 2,
      "reproduce": 91
    }
  },
  {
    "tick": 310,
    "population": 808,
    "avg_energy": 0.6049475278081754,
    "avg_age": 77.5878712871287,
    "avg_aggression": 0.30211496804158294,
    "avg_metabolism": 0.018637351852542745,
    "max_generation": 11,
    "births_this_period": 64,
    "deaths_this_period": 64,
    "species_counts": {
      "0": 38,
      "1": 125,
      "2": 192,
      "3": 347,
      "4": 106
    },
    "drive_distribution": {
      "hunger": 674,
      "fear": 26,
      "social": 0,
      "reproduce": 108
    }
  },
  {
    "tick": 320,
    "population": 818,
    "avg_energy": 0.6049717093507727,
    "avg_age": 78.84596577017115,
    "avg_aggression": 0.3001906425804559,
    "avg_metabolism": 0.01839713417108012,
    "max_generation": 11,
    "births_this_period": 65,
    "deaths_this_period": 55,
    "species_counts": {
      "0": 37,
      "1": 125,
      "2": 187,
      "3": 355,
      "4": 114
    },
    "drive_distribution": {
      "hunger": 703,
      "fear": 15,
      "social": 0,
      "reproduce": 100
    }
  },
  {
    "tick": 330,
    "population": 821,
    "avg_energy": 0.6059853886116434,
    "avg_age": 79.3836784409257,
    "avg_aggression": 0.2991293538303972,
    "avg_metabolism": 0.018171098052484364,
    "max_generation": 12,
    "births_this_period": 67,
    "deaths_this_period": 64,
    "species_counts": {
      "0": 36,
      "1": 119,
      "2": 189,
      "3": 361,
      "4": 116
    },
    "drive_distribution": {
      "hunger": 697,
      "fear": 17,
      "social": 0,
      "reproduce": 107
    }
  },
  {
    "tick": 340,
    "population": 835,
    "avg_energy": 0.6006454645704412,
    "avg_age": 80.92574850299401,
    "avg_aggression": 0.2984328059486326,
    "avg_metabolism": 0.01806059157788893,
    "max_generation": 12,
    "births_this_period": 65,
    "deaths_this_period": 51,
    "species_counts": {
      "0": 33,
      "1": 122,
      "2": 189,
      "3": 371,
      "4": 120
    },
    "drive_distribution": {
      "hunger": 703,
      "fear": 32,
      "social": 0,
      "reproduce": 100
    }
  },
  {
    "tick": 350,
    "population": 832,
    "avg_energy": 0.6114319918409564,
    "avg_age": 79.45432692307692,
    "avg_aggression": 0.2983430659126653,
    "avg_metabolism": 0.017975052976224436,
    "max_generation": 13,
    "births_this_period": 78,
    "deaths_this_period": 81,
    "species_counts": {
      "0": 30,
      "1": 126,
      "2": 186,
      "3": 376,
      "4": 114
    },
    "drive_distribution": {
      "hunger": 702,
      "fear": 22,
      "social": 0,
      "reproduce": 108
    }
  },
  {
    "tick": 360,
    "population": 840,
    "avg_energy": 0.6088580283787004,
    "avg_age": 79.41071428571429,
    "avg_aggression": 0.297258233356151,
    "avg_metabolism": 0.017767429826914635,
    "max_generation": 13,
    "births_this_period": 72,
    "deaths_this_period": 64,
    "species_counts": {
      "0": 30,
      "1": 126,
      "2": 192,
      "3": 383,
      "4": 109
    },
    "drive_distribution": {
      "hunger": 698,
      "fear": 30,
      "social": 0,
      "reproduce": 112
    }
  },
  {
    "tick": 370,
    "population": 848,
    "avg_energy": 0.6150575290357568,
    "avg_age": 79.55188679245283,
    "avg_aggression": 0.29848322202545885,
    "avg_metabolism": 0.017620296440476826,
    "max_generation": 13,
    "births_this_period": 71,
    "deaths_this_period": 63,
    "species_counts": {
      "0": 31,
      "1": 132,
      "2": 193,
      "3": 380,
      "4": 112
    },
    "drive_distribution": {
      "hunger": 712,
      "fear": 28,
      "social": 0,
      "reproduce": 108
    }
  },
  {
    "tick": 380,
    "population": 859,
    "avg_energy": 0.6178165579606844,
    "avg_age": 78.72759022118743,
    "avg_aggression": 0.2980707820930899,
    "avg_metabolism": 0.017462596055753142,
    "max_generation": 14,
    "births_this_period": 74,
    "deaths_this_period": 63,
    "species_counts": {
      "0": 29,
      "1": 136,
      "2": 189,
      "3": 395,
      "4": 110
    },
    "drive_distribution": {
      "hunger": 727,
      "fear": 33,
      "social": 0,
      "reproduce": 99
    }
  },
  {
    "tick": 390,
    "population": 881,
    "avg_energy": 0.6007860208115807,
    "avg_age": 79.56299659477867,
    "avg_aggression": 0.2966312625113801,
    "avg_metabolism": 0.01730082503298603,
    "max_generation": 14,
    "births_this_period": 75,
    "deaths_this_period": 53,
    "species_counts": {
      "0": 31,
      "1": 137,
      "2": 193,
      "3": 407,
      "4": 113
    },
    "drive_distribution": {
      "hunger": 734,
      "fear": 34,
      "social": 0,
      "reproduce": 113
    }
  },
  {
    "tick": 400,
    "population": 898,
    "avg_energy": 0.5941497107123596,
    "avg_age": 81.01113585746103,
    "avg_aggression": 0.2963827684815595,
    "avg_metabolism": 0.017186018634730953,
    "max_generation": 14,
    "births_this_period": 71,
    "deaths_this_period": 54,
    "species_counts": {
      "0": 33,
      "1": 131,
      "2": 199,
      "3": 420,
      "4": 115
    },
    "drive_distribution": {
      "hunger": 739,
      "fear": 47,
      "social": 0,
      "reproduce": 112
    }
  },
  {
    "tick": 410,
    "population": 906,
    "avg_energy": 0.6050121399436065,
    "avg_age": 80.3355408388521,
    "avg_aggression": 0.29525939718790895,
    "avg_metabolism": 0.017033589622824384,
    "max_generation": 15,
    "births_this_period": 78,
    "deaths_this_period": 70,
    "species_counts": {
      "0": 33,
      "1": 128,
      "2": 202,
      "3": 421,
      "4": 122
    },
    "drive_distribution": {
      "hunger": 769,
      "fear": 33,
      "social": 0,
      "reproduce": 104
    }
  },
  {
    "tick": 420,
    "population": 913,
    "avg_energy": 0.5958512184285946,
    "avg_age": 81.6078860898138,
    "avg_aggression": 0.29618188781636895,
    "avg_metabolism": 0.016855044249384978,
    "max_generation": 15,
    "births_this_period": 66,
    "deaths_this_period": 59,
    "species_counts": {
      "0": 33,
      "1": 121,
      "2": 213,
      "3": 422,
      "4": 124
    },
    "drive_distribution": {
      "hunger": 772,
      "fear": 39,
      "social": 1,
      "reproduce": 101
    }
  },
  {
    "tick": 430,
    "population": 920,
    "avg_energy": 0.5828836696668283,
    "avg_age": 80.90434782608696,
    "avg_aggression": 0.295531709276782,
    "avg_metabolism": 0.016649614958204797,
    "max_generation": 15,
    "births_this_period": 74,
    "deaths_this_period": 67,
    "species_counts": {
      "0": 33,
      "1": 118,
      "2": 217,
      "3": 431,
      "4": 121
    },
    "drive_distribution": {
      "hunger": 766,
      "fear": 43,
      "social": 0,
      "reproduce": 111
    }
  },
  {
    "tick": 440,
    "population": 926,
    "avg_energy": 0.5721957337077824,
    "avg_age": 81.90280777537797,
    "avg_aggression": 0.29431425483346374,
    "avg_metabolism": 0.01651221918437798,
    "max_generation": 16,
    "births_this_period": 73,
    "deaths_this_period": 67,
    "species_counts": {
      "0": 32,
      "1": 118,
      "2": 222,
      "3": 423,
      "4": 131
    },
    "drive_distribution": {
      "hunger": 785,
      "fear": 40,
      "social": 0,
      "reproduce": 101
    }
  },
  {
    "tick": 450,
    "population": 923,
    "avg_energy": 0.5871511438580342,
    "avg_age": 83.1830985915493,
    "avg_aggression": 0.2955124403074761,
    "avg_metabolism": 0.016446787820445556,
    "max_generation": 16,
    "births_this_period": 69,
    "deaths_this_period": 72,
    "species_counts": {
      "0": 30,
      "1": 122,
      "2": 226,
      "3": 410,
      "4": 135
    },
    "drive_distribution": {
      "hunger": 778,
      "fear": 39,
      "social": 0,
      "reproduce": 106
    }
  },
  {
    "tick": 460,
    "population": 926,
    "avg_energy": 0.585336744567514,
    "avg_age": 83.35961123110151,
    "avg_aggression": 0.29400808359394076,
    "avg_metabolism": 0.016264779913907745,
    "max_generation": 16,
    "births_this_period": 72,
    "deaths_this_period": 69,
    "species_counts": {
      "0": 28,
      "1": 119,
      "2": 229,
      "3": 406,
      "4": 144
    },
    "drive_distribution": {
      "hunger": 767,
      "fear": 41,
      "social": 0,
      "reproduce": 118
    }
  },
  {
    "tick": 470,
    "population": 952,
    "avg_energy": 0.582527399691751,
    "avg_age": 84.8970588235294,
    "avg_aggression": 0.29352074000910444,
    "avg_metabolism": 0.016144397629104412,
    "max_generation": 17,
    "births_this_period": 75,
    "deaths_this_period": 49,
    "species_counts": {
      "0": 29,
      "1": 127,
      "2": 231,
      "3": 409,
      "4": 156
    },
    "drive_distribution": {
      "hunger": 790,
      "fear": 48,
      "social": 0,
      "reproduce": 114
    }
  },
  {
    "tick": 480,
    "population": 961,
    "avg_energy": 0.5872511340331421,
    "avg_age": 83.19667013527575,
    "avg_aggression": 0.29409211435029625,
    "avg_metabolism": 0.016041117083443704,
    "max_generation": 17,
    "births_this_period": 80,
    "deaths_this_period": 71,
    "species_counts": {
      "0": 25,
      "1": 120,
      "2": 243,
      "3": 409,
      "4": 164
    },
    "drive_distribution": {
      "hunger": 818,
      "fear": 37,
      "social": 0,
      "reproduce": 106
    }
  },
  {
    "tick": 490,
    "population": 958,
    "avg_energy": 0.585168561841968,
    "avg_age": 82.50208768267224,
    "avg_aggression": 0.29427502759747687,
    "avg_metabolism": 0.015923430097899476,
    "max_generation": 18,
    "births_this_period": 70,
    "deaths_this_period": 73,
    "species_counts": {
      "0": 25,
      "1": 119,
      "2": 245,
      "3": 408,
      "4": 161
    },
    "drive_distribution": {
      "hunger": 812,
      "fear": 31,
      "social": 0,
      "reproduce": 115
    }
  },
  {
    "tick": 500,
    "population": 971,
    "avg_energy": 0.5892899369583867,
    "avg_age": 84.11534500514934,
    "avg_aggression": 0.2952162591253517,
    "avg_metabolism": 0.015828715304550392,
    "max_generation": 18,
    "births_this_period": 70,
    "deaths_this_period": 57,
    "species_counts": {
      "0": 26,
      "1": 121,
      "2": 246,
      "3": 411,
      "4": 167
    },
    "drive_distribution": {
      "hunger": 814,
      "fear": 35,
      "social": 0,
      "reproduce": 122
    }
  }
]