{
  "last_generation_time": 1779839041.3582838,
  "proposals_history": [
    {
      "time": "2026-05-26T13:36:12.301207",
      "count": 1,
      "top": "Improve User Alignment",
      "top_priority": 0.425
    },
    {
      "time": "2026-05-26T13:47:03.465278",
      "count": 1,
      "top": "Improve User Alignment",
      "top_priority": 0.425
    },
    {
      "time": "2026-05-26T13:54:16.692417",
      "count": 1,
      "top": "Improve User Alignment",
      "top_priority": 0.425
    },
    {
      "time": "2026-05-26T14:06:06.929776",
      "count": 1,
      "top": "Improve User Alignment",
      "top_priority": 0.425
    },
    {
      "time": "2026-05-26T14:12:00.392290",
      "count": 1,
      "top": "Improve User Alignment",
      "top_priority": 0.425
    },
    {
      "time": "2026-05-26T14:28:59.792492",
      "count": 1,
      "top": "Improve User Alignment",
      "top_priority": 0.425
    },
    {
      "time": "2026-05-26T14:34:01.364108",
      "count": 1,
      "top": "Improve User Alignment",
      "top_priority": 0.425
    },
    {
      "time": "2026-05-26T14:39:16.249932",
      "count": 1,
      "top": "Improve User Alignment",
      "top_priority": 0.425
    },
    {
      "time": "2026-05-26T14:53:36.671102",
      "count": 1,
      "top": "Improve User Alignment",
      "top_priority": 0.425
    },
    {
      "time": "2026-05-26T15:36:42.315296",
      "count": 1,
      "top": "Improve User Alignment",
      "top_priority": 0.425
    },
    {
      "time": "2026-05-26T15:41:57.740502",
      "count": 1,
      "top": "Improve User Alignment",
      "top_priority": 0.425
    },
    {
      "time": "2026-05-26T15:47:49.827954",
      "count": 1,
      "top": "Improve User Alignment",
      "top_priority": 0.425
    },
    {
      "time": "2026-05-26T15:53:01.758602",
      "count": 1,
      "top": "Improve User Alignment",
      "top_priority": 0.425
    },
    {
      "time": "2026-05-26T15:58:30.387730",
      "count": 1,
      "top": "Improve User Alignment",
      "top_priority": 0.425
    },
    {
      "time": "2026-05-26T16:05:47.701642",
      "count": 1,
      "top": "Improve User Alignment",
      "top_priority": 0.425
    },
    {
      "time": "2026-05-26T16:21:37.243495",
      "count": 1,
      "top": "Improve User Alignment",
      "top_priority": 0.425
    },
    {
      "time": "2026-05-26T16:26:48.744108",
      "count": 1,
      "top": "Improve User Alignment",
      "top_priority": 0.425
    },
    {
      "time": "2026-05-26T16:32:34.703799",
      "count": 1,
      "top": "Improve User Alignment",
      "top_priority": 0.425
    },
    {
      "time": "2026-05-26T16:37:46.472417",
      "count": 1,
      "top": "Improve User Alignment",
      "top_priority": 0.425
    },
    {
      "time": "2026-05-26T16:44:01.358285",
      "count": 1,
      "top": "Improve User Alignment",
      "top_priority": 0.425
    }
  ],
  "auto_adopted": [
    {
      "proposal_id": "reduce_boredom",
      "proposal_title": "Build Something Novel",
      "plan_id": 4,
      "adopted_at": "2026-05-16T04:48:59.624612",
      "priority": 0.695
    },
    {
      "proposal_id": "break_stagnation",
      "proposal_title": "Break Out of Stagnation",
      "plan_id": 7,
      "adopted_at": "2026-05-18T13:09:30.630765",
      "priority": 0.72
    },
    {
      "proposal_id": "revive_curiosity",
      "proposal_title": "Revive Declining Curiosity",
      "plan_id": 8,
      "adopted_at": "2026-05-19T12:12:46.734948",
      "priority": 0.75
    },
    {
      "proposal_id": "resolve_anxiety",
      "proposal_title": "Address Anxiety Hotspot",
      "plan_id": 9,
      "adopted_at": "2026-05-22T19:21:38.681973",
      "priority": 0.853
    }
  ],
  "total_generated": 1268,
  "total_adopted": 4
}